{
  "swagger": "2.0",
  "info": {
    "title": "Team 16's API",
    "description": "This API was created by Team 16 to manage events.<br><br><a href='/auth/google'>🔐 Log In with Google</a><br><a href='/auth/logout'>🚪 Log Out</a>",
    "version": "1.0.0"
  },
  "basePath": "/",
  "paths": {
    "/": {
      "get": {
        "tags": ["main"],
        "description": "",
        "responses": {
          "200": {
            "description": "OK"
          },
          "500": {
            "description": "Internal Server Error"
          }
        }
      },
      "post": {
        "tags": ["main"],
        "description": "",
        "parameters": [
          {
            "name": "body",
            "in": "body",
            "schema": {
              "type": "object",
              "properties": {
                "userId": {
                  "example": "any"
                },
                "userName": {
                  "example": "any"
                },
                "eventId": {
                  "example": "any"
                },
                "content": {
                  "example": "any"
                }
              }
            }
          }
        ],
        "responses": {
          "201": {
            "description": "Created"
          },
          "400": {
            "description": "Bad Request"
          }
        }
      }
    },
    "/api-docs": {
      "get": {
        "tags": ["Meta"],
        "description": "",
        "responses": {
          "default": {
            "description": ""
          }
        }
      }
    },
    "/auth/google": {
      "get": {
        "tags": ["Auth"],
        "description": "<a href='/auth/google'>Click here to Log In with Google</a>",
        "responses": {
          "200": {
            "description": "OK"
          }
        }
      }
    },
    "/auth/logout": {
      "get": {
        "tags": ["Auth"],
        "description": "<a href='/auth/logout'>🚪 Click here to Log Out</a>",
        "responses": {
          "200": {
            "description": "Logged Out"
          }
        }
      }
    },
    "/auth/google/callback": {
      "get": {
        "tags": ["Auth"],
        "description": "",
        "responses": {
          "default": {
            "description": ""
          }
        }
      }
    },
    "/auth/failure": {
      "get": {
        "tags": ["Auth"],
        "description": "",
        "responses": {
          "200": {
            "description": "OK"
          }
        }
      }
    },
    "/auth/success": {
      "get": {
        "tags": ["Auth"],
        "description": "",
        "responses": {
          "200": {
            "description": "OK"
          }
        }
      }
    },
    "/events/": {
      "get": {
        "tags": ["Events"],
        "description": "",
        "responses": {
          "200": {
            "description": "OK"
          },
          "500": {
            "description": "Internal Server Error"
          }
        }
      },
      "post": {
        "tags": ["Events"],
        "description": "",
        "parameters": [
          {
            "name": "body",
            "in": "body",
            "schema": {
              "type": "object",
              "properties": {
                "title": {
                  "example": "any"
                },
                "description": {
                  "example": "any"
                },
                "location": {
                  "example": "any"
                },
                "category": {
                  "example": "any"
                },
                "date": {
                  "example": "any"
                },
                "time": {
                  "example": "any"
                },
                "createdBy": {
                  "example": "any"
                }
              }
            }
          }
        ],
        "responses": {
          "201": {
            "description": "Created"
          },
          "400": {
            "description": "Bad Request"
          }
        }
      }
    },
    "/events/{id}": {
      "get": {
        "tags": ["Events"],
        "description": "",
        "parameters": [
          {
            "name": "id",
            "in": "path",
            "required": true,
            "type": "string"
          }
        ],
        "responses": {
          "200": {
            "description": "OK"
          },
          "404": {
            "description": "Not Found"
          },
          "500": {
            "description": "Internal Server Error"
          }
        }
      },
      "put": {
        "tags": ["Events"],
        "description": "",
        "parameters": [
          {
            "name": "id",
            "in": "path",
            "required": true,
            "type": "string"
          },
          {
            "name": "body",
            "in": "body",
            "schema": {
              "type": "object",
              "properties": {
                "title": {
                  "example": "any"
                },
                "description": {
                  "example": "any"
                },
                "location": {
                  "example": "any"
                },
                "category": {
                  "example": "any"
                },
                "date": {
                  "example": "any"
                },
                "time": {
                  "example": "any"
                },
                "createdBy": {
                  "example": "any"
                }
              }
            }
          }
        ],
        "responses": {
          "200": {
            "description": "OK"
          },
          "400": {
            "description": "Bad Request"
          },
          "404": {
            "description": "Not Found"
          },
          "500": {
            "description": "Internal Server Error"
          }
        }
      },
      "delete": {
        "tags": ["Events"],
        "description": "",
        "parameters": [
          {
            "name": "id",
            "in": "path",
            "required": true,
            "type": "string"
          }
        ],
        "responses": {
          "204": {
            "description": "No Content"
          },
          "404": {
            "description": "Not Found"
          },
          "500": {
            "description": "Internal Server Error"
          }
        }
      }
    },
    "/rsvps/": {
      "get": {
        "tags": [
          "RSVPs"
        ],
        "description": "",
        "responses": {
          "200": {
            "description": "OK"
          },
          "500": {
            "description": "Internal Server Error"
          }
        }
      },
      "post": {
        "tags": [
          "RSVPs"
        ],
        "description": "",
        "parameters": [
          {
            "name": "body",
            "in": "body",
            "schema": {
              "type": "object",
              "properties": {
                "userId": {
                  "example": "any"
                },
                "eventId": {
                  "example": "any"
                },
                "status": {
                  "example": "any"
                }
              }
            }
          }
        ],
        "responses": {
          "201": {
            "description": "Created"
          },
          "400": {
            "description": "Bad Request"
          },
          "401": {
            "description": "Unauthorized"
          }
        }
      }
    },
    "/rsvps/{id}": {
      "get": {
        "tags": [
          "RSVPs"
        ],
        "description": "",
        "parameters": [
          {
            "name": "id",
            "in": "path",
            "required": true,
            "type": "string"
          }
        ],
        "responses": {
          "200": {
            "description": "OK"
          },
          "404": {
            "description": "Not Found"
          },
          "500": {
            "description": "Internal Server Error"
          }
        }
      },
      "put": {
        "tags": [
          "RSVPs"
        ],
        "description": "",
        "parameters": [
          {
            "name": "id",
            "in": "path",
            "required": true,
            "type": "string"
          },
          {
            "name": "body",
            "in": "body",
            "schema": {
              "type": "object",
              "properties": {
                "userId": {
                  "example": "any"
                },
                "eventId": {
                  "example": "any"
                },
                "status": {
                  "example": "any"
                }
              }
            }
          }
        ],
        "responses": {
          "200": {
            "description": "OK"
          },
          "400": {
            "description": "Bad Request"
          },
          "401": {
            "description": "Unauthorized"
          },
          "404": {
            "description": "Not Found"
          }
        }
      },
      "delete": {
        "tags": [
          "RSVPs"
        ],
        "description": "",
        "parameters": [
          {
            "name": "id",
            "in": "path",
            "required": true,
            "type": "string"
          }
        ],
        "responses": {
          "204": {
            "description": "No Content"
          },
          "401": {
            "description": "Unauthorized"
          },
          "404": {
            "description": "Not Found"
          },
          "500": {
            "description": "Internal Server Error"
          }
        }
      }
    },
    "/organizations/": {
      "get": {
        "tags": ["Organizations"],
        "description": "",
        "responses": {
          "200": {
            "description": "OK"
          },
          "500": {
            "description": "Internal Server Error"
          }
        }
      },
      "post": {
        "tags": ["Organizations"],
        "description": "",
        "parameters": [
          {
            "name": "body",
            "in": "body",
            "schema": {
              "type": "object",
              "properties": {
                "name": {
                  "example": "any"
                },
                "description": {
                  "example": "any"
                },
                "address": {
                  "example": "any"
                },
                "email": {
                  "example": "any"
                },
                "phone": {
                  "example": "any"
                },
                "website": {
                  "example": "any"
                },
                "createdBy": {
                  "example": "any"
                }
              }
            }
          }
        ],
        "responses": {
          "201": {
            "description": "Created"
          },
          "400": {
            "description": "Bad Request"
          }
        }
      }
    },
    "/organizations/{id}": {
      "get": {
        "tags": ["Organizations"],
        "description": "",
        "parameters": [
          {
            "name": "id",
            "in": "path",
            "required": true,
            "type": "string"
          }
        ],
        "responses": {
          "200": {
            "description": "OK"
          },
          "404": {
            "description": "Not Found"
          },
          "500": {
            "description": "Internal Server Error"
          }
        }
      },
      "put": {
        "tags": ["Organizations"],
        "description": "",
        "parameters": [
          {
            "name": "id",
            "in": "path",
            "required": true,
            "type": "string"
          },
          {
            "name": "body",
            "in": "body",
            "schema": {
              "type": "object",
              "properties": {
                "name": {
                  "example": "any"
                },
                "description": {
                  "example": "any"
                },
                "address": {
                  "example": "any"
                },
                "email": {
                  "example": "any"
                },
                "phone": {
                  "example": "any"
                },
                "website": {
                  "example": "any"
                },
                "createdBy": {
                  "example": "any"
                }
              }
            }
          }
        ],
        "responses": {
          "200": {
            "description": "OK"
          },
          "400": {
            "description": "Bad Request"
          },
          "404": {
            "description": "Not Found"
          },
          "500": {
            "description": "Internal Server Error"
          }
        }
      },
      "delete": {
        "tags": ["Organizations"],
        "description": "",
        "parameters": [
          {
            "name": "id",
            "in": "path",
            "required": true,
            "type": "string"
          }
        ],
        "responses": {
          "204": {
            "description": "No Content"
          },
          "404": {
            "description": "Not Found"
          },
          "500": {
            "description": "Internal Server Error"
          }
        }
      }
    },
    "/locations": {
      "get": {
        "tags": ["Locations"],
        "description": "Get all locations",
        "responses": {
          "200": {
            "description": "OK"
          },
          "500": {
            "description": "Internal Server Error"
          }
        }
      },
      "post": {
        "tags": ["Locations"],
        "description": "Protected: Create a new location (requires Google OAuth login via /auth/google).",
        "parameters": [
          {
            "name": "body",
            "in": "body",
            "schema": {
              "type": "object",
              "properties": {
                "name": {
                  "example": "Calgary Ballroom"
                },
                "type": {
                  "example": "hall"
                },
                "address": {
                  "example": "100 Main Street SE"
                },
                "city": {
                  "example": "Calgary"
                },
                "stateOrProvince": {
                  "example": "AB"
                },
                "country": {
                  "example": "Canada"
                },
                "recommendedFor": {
                  "type": "array",
                  "items": {
                    "type": "string",
                    "example": "wedding"
                  }
                }
              }
            }
          }
        ],
        "responses": {
          "201": {
            "description": "Created"
          },
          "400": {
            "description": "Bad Request"
          },
          "401": {
            "description": "Unauthorized - Please log in via Google OAuth"
          }
        }
      }
    },
    "/locations/{id}": {
      "get": {
        "tags": ["Locations"],
        "description": "Get a single location by ID",
        "parameters": [
          {
            "name": "id",
            "in": "path",
            "required": true,
            "type": "string"
          }
        ],
        "responses": {
          "200": {
            "description": "OK"
          },
          "404": {
            "description": "Not Found"
          },
          "500": {
            "description": "Internal Server Error"
          }
        }
      },
      "put": {
        "tags": ["Locations"],
        "description": "Protected: Update a location by ID (requires Google OAuth login via /auth/google).",
        "parameters": [
          {
            "name": "id",
            "in": "path",
            "required": true,
            "type": "string"
          },
          {
            "name": "body",
            "in": "body",
            "schema": {
              "type": "object",
              "properties": {
                "name": {
                  "example": "Calgary Ballroom"
                },
                "type": {
                  "example": "hall"
                },
                "address": {
                  "example": "100 Main Street SE"
                },
                "city": {
                  "example": "Calgary"
                },
                "stateOrProvince": {
                  "example": "AB"
                },
                "country": {
                  "example": "Canada"
                },
                "recommendedFor": {
                  "type": "array",
                  "items": {
                    "type": "string",
                    "example": "wedding"
                  }
                }
              }
            }
          }
        ],
        "responses": {
          "200": {
            "description": "OK"
          },
          "400": {
            "description": "Bad Request"
          },
          "401": {
            "description": "Unauthorized - Please log in via Google OAuth"
          },
          "404": {
            "description": "Not Found"
          },
          "500": {
            "description": "Internal Server Error"
          }
        }
      },
      "delete": {
        "tags": ["Locations"],
        "description": "Protected: Delete a location by ID (requires Google OAuth login via /auth/google).",
        "parameters": [
          {
            "name": "id",
            "in": "path",
            "required": true,
            "type": "string"
          }
        ],
        "responses": {
          "204": {
            "description": "No Content"
          },
          "404": {
            "description": "Not Found"
          },
          "500": {
            "description": "Internal Server Error"
          }
        }
      }
    },
"/comments": {
  "get": {
    "tags": ["comments"],
    "description": "Get all comments",
    "parameters": [],
    "responses": {
      "200": { "description": "OK" },
      "404": { "description": "Not Found" },
      "500": { "description": "Internal Server Error" }
    }
  },

  "post": {
    "tags": ["comments"],
    "description": "Create a new comment",
    "parameters": [
      {
        "name": "body",
        "in": "body",
        "required": true,
        "schema": {
          "type": "object",
          "required": ["userId", "userName", "eventId", "content"],
          "properties": {
            "userId": { "type": "string", "example": "675a3bd91c4e45d3a8d2f116" },
            "userName": { "type": "string", "example": "Daniel Rivera" },
            "eventId": { "type": "string", "example": "6781f0b48e9c55a5b23c9310" },
            "content": { "type": "string", "example": "Let me know if I can help with anything before the event." }
          }
        }
      }
    ],
    "responses": {
      "200": { "description": "OK" },
      "400": { "description": "Bad Request" },
      "404": { "description": "Not Found" },
      "500": { "description": "Internal Server Error" }
    }
  }
},

"/comments/{id}": {
  "get": {
    "tags": ["comments"],
    "description": "Get a comment by ID",
    "parameters": [
      {
        "name": "id",
        "in": "path",
        "required": true,
        "type": "string"
      }
    ],
    "responses": {
      "200": { "description": "OK" },
      "404": { "description": "Not Found" },
      "500": { "description": "Internal Server Error" }
    }
  },

  "put": {
    "tags": ["comments"],
    "description": "Update a comment by ID",
    "parameters": [
      {
        "name": "id",
        "in": "path",
        "required": true,
        "type": "string"
      },
      {
        "name": "body",
        "in": "body",
        "required": true,
        "schema": {
          "type": "object",
          "required": ["userId", "userName", "eventId", "content"],
          "properties": {
            "userId": { "type": "string", "example": "675a3bd91c4e45d3a8d2f116" },
            "userName": { "type": "string", "example": "Daniel Rivera" },
            "eventId": { "type": "string", "example": "6781f0b48e9c55a5b23c9310" },
            "content": { "type": "string", "example": "Updated comment content" }
          }
        }
      }
    ],
    "responses": {
      "200": { "description": "OK" },
      "400": { "description": "Bad Request" },
      "404": { "description": "Not Found" },
      "500": { "description": "Internal Server Error" }
    }
  },

  "delete": {
    "tags": ["comments"],
    "description": "Delete a comment by ID",
    "parameters": [
      {
        "name": "id",
        "in": "path",
        "required": true,
        "type": "string"
      }
    ],
    "responses": {
      "204": { "description": "No Content" },
      "404": { "description": "Not Found" },
      "500": { "description": "Internal Server Error" }
    }
  }
},
"/orders/{userId}": {
      "get": {
        "tags": ["Orders"],
        "summary": "Get user's orders",
        "description": "Get all orders for the specific user with optional filtering and pagination",
        "parameters": [
          {
            "name": "userId",
            "in": "path",
            "required": true,
            "type": "string",
            "description": "User ID"
          },
          {
            "name": "status",
            "in": "query",
            "type": "string",
            "enum": ["pending", "paid", "cancelled"],
            "description": "Filter orders by status"
          },
          {
            "name": "sort",
            "in": "query",
            "type": "string",
            "default": "createdAt",
            "description": "Field to sort by"
          },
          {
            "name": "order",
            "in": "query",
            "type": "string",
            "enum": ["asc", "desc"],
            "default": "desc",
            "description": "Sort order"
          },
          {
            "name": "page",
            "in": "query",
            "type": "integer",
            "default": 1,
            "description": "Page number"
          },
          {
            "name": "limit",
            "in": "query",
            "type": "integer",
            "default": 10,
            "description": "Items per page"
          }
        ],
        "responses": {
          "200": {
            "description": "Orders retrieved successfully",
            "schema": {
              "type": "object",
              "properties": {
                "data": {
                  "type": "array",
                  "items": {
                    "type": "object"
                  }
                },
                "total": {
                  "type": "integer"
                },
                "page": {
                  "type": "integer"
                },
                "pages": {
                  "type": "integer"
                }
              }
            }
          },
          "500": {
            "description": "Internal Server Error"
          }
        }
      }
    },
    "/orders/": {
      "post": {
        "tags": ["Orders"],
        "summary": "Create a new order",
        "description": "Create a new order with ticket tiers from the same event",
        "parameters": [
          {
            "name": "body",
            "in": "body",
            "required": true,
            "schema": {
              "type": "object",
              "properties": {
                "userId": {
                  "type": "string",
                  "description": "User ID"
                },
                "eventId": {
                  "type": "string",
                  "description": "Event ID"
                },
                "items": {
                  "type": "array",
                  "description": "Array of ticket tier items",
                  "items": {
                    "type": "object",
                    "properties": {
                      "tierId": {
                        "type": "string",
                        "description": "Ticket tier ID"
                      },
                      "quantity": {
                        "type": "number",
                        "description": "Number of tickets"
                      }
                    }
                  }
                },
                "holder_info": {
                  "type": "object",
                  "properties": {
                    "name": {
                      "type": "string"
                    },
                    "email": {
                      "type": "string"
                    },
                    "identification_number": {
                      "type": "string"
                    }
                  }
                }
              }
            }
          }
        ],
        "responses": {
          "201": {
            "description": "Order created successfully"
          },
          "400": {
            "description": "Validation errors - insufficient stock or items from different events"
          },
          "500": {
            "description": "Internal Server Error"
          }
        }
      }
    },
    "/orders/{id}/pay": {
      "post": {
        "tags": ["Orders"],
        "summary": "Confirm payment for order",
        "description": "Confirm payment and generate tickets for the order",
        "parameters": [
          {
            "name": "id",
            "in": "path",
            "required": true,
            "type": "string",
            "description": "Order ID"
          },
          {
            "name": "body",
            "in": "body",
            "required": true,
            "schema": {
              "type": "object",
              "properties": {
                "userId": {
                  "type": "string",
                  "description": "User ID"
                },
                "payment_id": {
                  "type": "string",
                  "description": "Payment ID from payment processor"
                },
                "holder_info": {
                  "type": "object",
                  "properties": {
                    "name": {
                      "type": "string"
                    },
                    "email": {
                      "type": "string"
                    },
                    "identification_number": {
                      "type": "string"
                    }
                  }
                }
              }
            }
          }
        ],
        "responses": {
          "200": {
            "description": "Payment confirmed and tickets issued",
            "schema": {
              "type": "object",
              "properties": {
                "message": {
                  "type": "string"
                },
                "data": {
                  "type": "object",
                  "properties": {
                    "order": {
                      "type": "object"
                    },
                    "tickets": {
                      "type": "array",
                      "items": {
                        "type": "object"
                      }
                    }
                  }
                }
              }
            }
          },
          "404": {
            "description": "Order not found"
          },
          "400": {
            "description": "Order already paid or cancelled"
          },
          "500": {
            "description": "Internal Server Error"
          }
        }
      }
    },
    "/orders/{orderId}": {
      "delete": {
        "tags": ["Orders"],
        "summary": "Delete an order",
        "description": "Delete an order by ID",
        "parameters": [
          {
            "name": "orderId",
            "in": "path",
            "required": true,
            "type": "string",
            "description": "Order ID"
          }
        ],
        "responses": {
          "200": {
            "description": "Order deleted successfully"
          },
          "404": {
            "description": "Order not found"
          },
          "500": {
            "description": "Internal Server Error"
          }
        }
      }
    },
    "/tickets/my-tickets/{userId}": {
      "get": {
        "tags": ["Tickets"],
        "summary": "Get user's tickets",
        "description": "Get all tickets for the specific user with optional filtering and pagination",
        "parameters": [
          {
            "name": "userId",
            "in": "path",
            "required": true,
            "type": "string",
            "description": "User ID"
          },
          {
            "name": "is_active",
            "in": "query",
            "type": "boolean",
            "description": "Filter by active status"
          },
          {
            "name": "status",
            "in": "query",
            "type": "string",
            "enum": ["active", "cancelled", "used"],
            "description": "Filter by ticket status"
          },
          {
            "name": "sort",
            "in": "query",
            "type": "string",
            "default": "createdAt",
            "description": "Field to sort by"
          },
          {
            "name": "order",
            "in": "query",
            "type": "string",
            "enum": ["asc", "desc"],
            "default": "asc",
            "description": "Sort order"
          },
          {
            "name": "page",
            "in": "query",
            "type": "integer",
            "default": 1,
            "description": "Page number"
          },
          {
            "name": "limit",
            "in": "query",
            "type": "integer",
            "default": 10,
            "description": "Items per page"
          }
        ],
        "responses": {
          "200": {
            "description": "Tickets retrieved successfully",
            "schema": {
              "type": "object",
              "properties": {
                "ok": {
                  "type": "boolean"
                },
                "data": {
                  "type": "array",
                  "items": {
                    "type": "object"
                  }
                },
                "total": {
                  "type": "integer"
                },
                "page": {
                  "type": "integer"
                },
                "pages": {
                  "type": "integer"
                }
              }
            }
          },
          "500": {
            "description": "Server error"
          }
        }
      }
    },
    "/tickets/{ticketId}/{userId}": {
      "get": {
        "tags": ["Tickets"],
        "summary": "Get ticket details",
        "description": "Get details of a specific ticket for the authenticated user",
        "parameters": [
          {
            "name": "ticketId",
            "in": "path",
            "required": true,
            "type": "string",
            "description": "Ticket ID"
          },
          {
            "name": "userId",
            "in": "path",
            "required": true,
            "type": "string",
            "description": "User ID"
          }
        ],
        "responses": {
          "200": {
            "description": "Ticket details retrieved successfully"
          },
          "404": {
            "description": "Ticket not found for this user"
          },
          "500": {
            "description": "Server error"
          }
        }
      }
    },
    "/tickets/{ticketId}/nominated-holder": {
      "put": {
        "tags": ["Tickets"],
        "summary": "Update ticket holder information",
        "description": "Update the nominated holder information for a ticket",
        "parameters": [
          {
            "name": "ticketId",
            "in": "path",
            "required": true,
            "type": "string",
            "description": "Ticket ID"
          },
          {
            "name": "body",
            "in": "body",
            "required": true,
            "schema": {
              "type": "object",
              "properties": {
                "name": {
                  "type": "string",
                  "description": "Holder name"
                },
                "identification_number": {
                  "type": "string",
                  "description": "Holder identification number"
                },
                "email": {
                  "type": "string",
                  "description": "Holder email"
                }
              }
            }
          }
        ],
        "responses": {
          "200": {
            "description": "Ticket holder updated successfully"
          },
          "404": {
            "description": "Ticket not found or not owned by user"
          },
          "500": {
            "description": "Server error"
          }
        }
      }
    },
    "/tickets/": {
      "get": {
        "tags": ["Tickets"],
        "summary": "Get all tickets",
        "description": "Get all tickets with optional filtering and pagination (admin endpoint)",
        "parameters": [
          {
            "name": "is_active",
            "in": "query",
            "type": "boolean",
            "description": "Filter by active status"
          },
          {
            "name": "status",
            "in": "query",
            "type": "string",
            "enum": ["active", "cancelled", "used"],
            "description": "Filter by ticket status"
          },
          {
            "name": "eventId",
            "in": "query",
            "type": "string",
            "description": "Filter by event ID"
          },
          {
            "name": "sort",
            "in": "query",
            "type": "string",
            "description": "Field to sort by"
          },
          {
            "name": "order",
            "in": "query",
            "type": "string",
            "enum": ["asc", "desc"],
            "default": "asc",
            "description": "Sort order"
          },
          {
            "name": "page",
            "in": "query",
            "type": "integer",
            "default": 1,
            "description": "Page number"
          },
          {
            "name": "limit",
            "in": "query",
            "type": "integer",
            "default": 10,
            "description": "Items per page"
          }
        ],
        "responses": {
          "200": {
            "description": "Tickets retrieved successfully"
          },
          "500": {
            "description": "Server error"
          }
        }
      }
    },
    "/tickets/{id}/cancel": {
      "post": {
        "tags": ["Tickets"],
        "summary": "Cancel a ticket",
        "description": "Cancel a ticket by ID",
        "parameters": [
          {
            "name": "id",
            "in": "path",
            "required": true,
            "type": "string",
            "description": "Ticket ID"
          }
        ],
        "responses": {
          "200": {
            "description": "Ticket cancelled successfully"
          },
          "404": {
            "description": "Ticket not found"
          },
          "400": {
            "description": "Ticket is already cancelled"
          },
          "500": {
            "description": "Server error"
          }
        }
      }
    },
    "/tickets/validate-entry": {
      "post": {
        "tags": ["Tickets"],
        "summary": "Validate ticket for entry",
        "description": "Validate a ticket using QR code hash and mark as used",
        "parameters": [
          {
            "name": "body",
            "in": "body",
            "required": true,
            "schema": {
              "type": "object",
              "properties": {
                "ticketCode": {
                  "type": "string",
                  "description": "QR hash of the ticket"
                }
              }
            }
          }
        ],
        "responses": {
          "200": {
            "description": "Ticket is valid for entry"
          },
          "404": {
            "description": "Ticket not found"
          },
          "400": {
            "description": "Ticket is not valid for entry"
          },
          "500": {
            "description": "Server error"
          }
        }

        
      }
    },
        "/ticket_tier/": {
      "get": {
        "tags": [
          "TicketTier"
        ],
        "summary": "Get all ticket tiers",
        "parameters": [
          {
            "name": "is_active",
            "in": "query",
            "type": "boolean"
          },
          {
            "name": "min_price",
            "in": "query",
            "type": "number"
          },
          {
            "name": "max_price",
            "in": "query",
            "type": "number"
          },
          {
            "name": "sort",
            "in": "query",
            "type": "string"
          },
          {
            "name": "order",
            "in": "query",
            "type": "string",
            "enum": [
              "asc",
              "desc"
            ]
          },
          {
            "name": "page",
            "in": "query",
            "type": "integer"
          },
          {
            "name": "limit",
            "in": "query",
            "type": "integer"
          }
        ],
        "responses": {
          "200": {
            "description": "OK"
          },
          "500": {
            "description": "Internal Server Error"
          }
        }
      },
      "post": {
        "tags": [
          "TicketTier"
        ],
        "summary": "Create a ticket tier",
        "parameters": [
          {
            "name": "body",
            "in": "body",
            "schema": {
              "type": "object",
              "properties": {
                "eventId": {
                  "type": "string"
                },
                "name": {
                  "type": "string"
                },
                "description": {
                  "type": "string"
                },
                "price": {
                  "type": "number"
                },
                "currency": {
                  "type": "string"
                },
                "capacity": {
                  "type": "number"
                },
                "sold": {
                  "type": "number"
                },
                "reserved": {
                  "type": "number"
                },
                "max_per_order": {
                  "type": "number"
                },
                "sales_start": {
                  "type": "string",
                  "format": "date-time"
                },
                "sales_end": {
                  "type": "string",
                  "format": "date-time"
                },
                "is_active": {
                  "type": "boolean"
                }
              }
            }
          }
        ],
        "responses": {
          "201": {
            "description": "Created"
          },
          "400": {
            "description": "Bad Request"
          }
        }
      }
    },
    "/ticket_tier/{id}": {
      "get": {
        "tags": [
          "TicketTier"
        ],
        "summary": "Get ticket tier by ID",
        "parameters": [
          {
            "name": "id",
            "in": "path",
            "required": true,
            "type": "string"
          }
        ],
        "responses": {
          "200": {
            "description": "OK"
          },
          "404": {
            "description": "Not Found"
          },
          "500": {
            "description": "Internal Server Error"
          }
        }
      },
      "put": {
        "tags": [
          "TicketTier"
        ],
        "summary": "Update ticket tier by ID",
        "parameters": [
          {
            "name": "id",
            "in": "path",
            "required": true,
            "type": "string"
          },
          {
            "name": "body",
            "in": "body",
            "schema": {
              "type": "object",
              "properties": {
                "eventId": {
                  "type": "string"
                },
                "name": {
                  "type": "string"
                },
                "description": {
                  "type": "string"
                },
                "price": {
                  "type": "number"
                },
                "currency": {
                  "type": "string"
                },
                "capacity": {
                  "type": "number"
                },
                "sold": {
                  "type": "number"
                },
                "reserved": {
                  "type": "number"
                },
                "max_per_order": {
                  "type": "number"
                },
                "sales_start": {
                  "type": "string",
                  "format": "date-time"
                },
                "sales_end": {
                  "type": "string",
                  "format": "date-time"
                },
                "is_active": {
                  "type": "boolean"
                }
              }
            }
          }
        ],
        "responses": {
          "200": {
            "description": "OK"
          },
          "400": {
            "description": "Bad Request"
          },
          "404": {
            "description": "Not Found"
          },
          "500": {
            "description": "Internal Server Error"
          }
        }
      },
      "delete": {
        "tags": [
          "TicketTier"
        ],
        "summary": "Delete ticket tier by ID",
        "parameters": [
          {
            "name": "id",
            "in": "path",
            "required": true,
            "type": "string"
          }
        ],
        "responses": {
          "200": {
            "description": "Deleted successfully"
          },
          "404": {
            "description": "Not Found"
          },
          "500": {
            "description": "Internal Server Error"
          }
        }
      }
    },
    "/ticket_tier/event/{eventId}": {
      "get": {
        "tags": [
          "TicketTier"
        ],
        "summary": "Get ticket tiers by event ID",
        "parameters": [
          {
            "name": "eventId",
            "in": "path",
            "required": true,
            "type": "string"
          }
        ],
        "responses": {
          "200": {
            "description": "OK"
          },
          "500": {
            "description": "Internal Server Error"
          }
        }
      }
    }
    }
  }